potemkin/__init__.py
potemkin/app.py
potemkin/routes.py
potemkin/views.py
potemkin/static/formsubmit.js
potemkin/static/pyramid-16x16.png
potemkin/static/pyramid.png
potemkin/static/theme.css
potemkin/templates/layout.jinja2
potemkin/templates/ltilaunch_form.html.jinja2
potemkin/templates/ltilaunch_iframe.html.jinja2
potemkin-0.0.dist-info/METADATA
potemkin-0.0.dist-info/RECORD
potemkin-0.0.dist-info/WHEEL
potemkin-0.0.dist-info/entry_points.txt
potemkin-0.0.dist-info/top_level.txt
