Metadata-Version: 2.1
Name: potemkin
Version: 0.0
Summary: potemkin
Home-page: UNKNOWN
Author: 
Author-email: 
License: UNKNOWN
Keywords: web pyramid pylons
Platform: UNKNOWN
Classifier: Programming Language :: Python
Classifier: Framework :: Pyramid
Classifier: Topic :: Internet :: WWW/HTTP
Classifier: Topic :: Internet :: WWW/HTTP :: WSGI :: Application
Provides-Extra: testing
Requires-Dist: oauthlib
Requires-Dist: plaster-pastedeploy
Requires-Dist: pyramid
Requires-Dist: pyramid-jinja2
Requires-Dist: pyramid-debugtoolbar
Requires-Dist: waitress
Provides-Extra: testing
Requires-Dist: WebTest (>=1.3.1); extra == 'testing'
Requires-Dist: pytest; extra == 'testing'
Requires-Dist: pytest-cov; extra == 'testing'
